odoo/addons/account_check_printing_report_dlt103/README.rst
odoo/addons/account_check_printing_report_dlt103/__init__.py
odoo/addons/account_check_printing_report_dlt103/__manifest__.py
odoo/addons/account_check_printing_report_dlt103/data/account_payment_check_report_data.xml
odoo/addons/account_check_printing_report_dlt103/data/report_paperformat.xml
odoo/addons/account_check_printing_report_dlt103/data/report_paperformat_parameter.xml
odoo/addons/account_check_printing_report_dlt103/i18n/account_check_printing_report_dlt103.pot
odoo/addons/account_check_printing_report_dlt103/i18n/pt.po
odoo/addons/account_check_printing_report_dlt103/readme/CONFIGURE.rst
odoo/addons/account_check_printing_report_dlt103/readme/CONTRIBUTORS.rst
odoo/addons/account_check_printing_report_dlt103/readme/DESCRIPTION.rst
odoo/addons/account_check_printing_report_dlt103/readme/INSTALL.rst
odoo/addons/account_check_printing_report_dlt103/readme/USAGE.rst
odoo/addons/account_check_printing_report_dlt103/report/__init__.py
odoo/addons/account_check_printing_report_dlt103/report/account_check_writing_report.xml
odoo/addons/account_check_printing_report_dlt103/report/check_print.py
odoo/addons/account_check_printing_report_dlt103/static/description/icon.png
odoo/addons/account_check_printing_report_dlt103/static/description/index.html
odoo/addons/account_check_printing_report_dlt103/views/report_check_dlt103.xml
odoo12_addon_account_check_printing_report_dlt103-12.0.1.0.0.99.dev6.dist-info/METADATA
odoo12_addon_account_check_printing_report_dlt103-12.0.1.0.0.99.dev6.dist-info/WHEEL
odoo12_addon_account_check_printing_report_dlt103-12.0.1.0.0.99.dev6.dist-info/top_level.txt
odoo12_addon_account_check_printing_report_dlt103-12.0.1.0.0.99.dev6.dist-info/RECORD
