Metadata-Version: 2.1
Name: odoo12-addon-account-check-printing-report-dlt103
Version: 12.0.1.0.0.99.dev6
Summary: Account Check Printing Report DLT103
Home-page: https://github.com/OCA/account-payment
Author: Eficent,Serpent Consulting Services Pvt. Ltd.,Odoo Community Association (OCA)
Author-email: support@odoo-community.org
License: AGPL-3
Platform: UNKNOWN
Classifier: Programming Language :: Python
Classifier: Framework :: Odoo
Classifier: Framework :: Odoo :: 12.0
Classifier: License :: OSI Approved :: GNU Affero General Public License v3
Requires-Python: >=3.5
Requires-Dist: odoo12-addon-account-check-printing-report-base
Requires-Dist: odoo <12.1dev,>=12.0a
